setup.py
test/test.py
tkitNextSents/__init__.py
tkitNextSents/nextsents.py
tkitNextSents.egg-info/PKG-INFO
tkitNextSents.egg-info/SOURCES.txt
tkitNextSents.egg-info/dependency_links.txt
tkitNextSents.egg-info/requires.txt
tkitNextSents.egg-info/top_level.txt